setup.py
qrcode_terminal/__init__.py
qrcode_terminal/qrcode_terminal.py
qrcode_terminal.egg-info/PKG-INFO
qrcode_terminal.egg-info/SOURCES.txt
qrcode_terminal.egg-info/dependency_links.txt
qrcode_terminal.egg-info/entry_points.txt
qrcode_terminal.egg-info/requires.txt
qrcode_terminal.egg-info/top_level.txt