Metadata-Version: 1.0
Name: qrcode-terminal
Version: 0.8
Summary: Python QRCode Terminal
Home-page: https://github.com/alishtory/qrcode-terminal
Author: UNKNOWN
Author-email: 840652591@qq.com
License: MIT
Platform: any
